inferno_ml/__init__.py
inferno_ml/accelerate.py
tests/__init__.py
tests/test_accelerate.py
inferno_ml-0.1.0.dist-info/LICENSE
inferno_ml-0.1.0.dist-info/METADATA
inferno_ml-0.1.0.dist-info/WHEEL
inferno_ml-0.1.0.dist-info/top_level.txt
inferno_ml-0.1.0.dist-info/RECORD
